meocloud/__init__.py
meocloud/cli.py
meocloud/services.py
meocloud-0.0.2.dist-info/METADATA
meocloud-0.0.2.dist-info/WHEEL
meocloud-0.0.2.dist-info/entry_points.txt
meocloud-0.0.2.dist-info/top_level.txt
meocloud-0.0.2.dist-info/RECORD
