Metadata-Version: 2.1
Name: meocloud
Version: 0.0.2
Summary: unofficial meocloud package
Home-page: https://github.com/IgorDantasID/meocloud
Author: Igor Dantas de Aguiar
Author-email: igordantas91@icloud.com
License: MIT
Platform: UNKNOWN
Classifier: Programming Language :: Python :: 3
Classifier: License :: OSI Approved :: MIT License
Classifier: Operating System :: OS Independent
Requires-Python: >=3.7
Requires-Dist: click (>=7.1.2)
Requires-Dist: requests-oauthlib (>=1.3.0)
Requires-Dist: requests (>=2.25.0)
